MANIFEST.in
README.html
README.txt
ez_setup.py
pdfnup
pdfnup.py
setup.cfg
setup.py
test_pdfnup.py
pdfnup.egg-info/PKG-INFO
pdfnup.egg-info/SOURCES.txt
pdfnup.egg-info/dependency_links.txt
pdfnup.egg-info/not-zip-safe
pdfnup.egg-info/requires.txt
pdfnup.egg-info/top_level.txt
samples/genpdf.py
samples/test-a4-l-16up.pdf
samples/test-a4-l-18up.pdf
samples/test-a4-l-2up.pdf
samples/test-a4-l-4up-fromFileObj.pdf
samples/test-a4-l-4up-fromStringIO.pdf
samples/test-a4-l-4up.pdf
samples/test-a4-l-8up.pdf
samples/test-a4-l-9up.pdf
samples/test-a4-l-toFileObj.pdf
samples/test-a4-l-toStringIO.pdf
samples/test-a4-l.pdf
samples/test-a4-lr-2up.pdf
samples/test-a4-lr-4up.pdf
samples/test-a4-lr-8up.pdf
samples/test-a4-lr-9up.pdf
samples/test-a4-lr.pdf
samples/test-a4-p-16up.pdf
samples/test-a4-p-18up.pdf
samples/test-a4-p-2up.pdf
samples/test-a4-p-4up.pdf
samples/test-a4-p-8up.pdf
samples/test-a4-p-9up.pdf
samples/test-a4-p.pdf
samples/test-a4-pr-2up.pdf
samples/test-a4-pr-4up.pdf
samples/test-a4-pr-8up.pdf
samples/test-a4-pr-9up.pdf
samples/test-a4-pr.pdf
samples/test-legal-p-2up.pdf
samples/test-legal-p-4up.pdf
samples/test-legal-p-8up.pdf
samples/test-legal-p-9up.pdf
samples/test-legal-p.pdf